dunderdoc
