Metadata-Version: 1.1
Name: dunderdoc
Version: 0.3.0
Summary: A Documentation module for dunder methods
Home-page: https://github.com/nhumrich/dunderdoc
Author: nhumrich
Author-email: UNKNOWN
License: MIT
Platform: UNKNOWN
Requires: click
